LICENSE
MANIFEST.in
README.rst
setup.py
eek/__init__.py
eek/eek
eek/robotparser.py
eek/spider.py
eek/test.py
eek.egg-info/PKG-INFO
eek.egg-info/SOURCES.txt
eek.egg-info/dependency_links.txt
eek.egg-info/requires.txt
eek.egg-info/top_level.txt