Metadata-Version: 1.0
Name: eek
Version: 1.0.2
Summary: Eek, a [web] spider.
Home-page: https://github.com/fusionbox/eek
Author: Gavin Wahl
Author-email: gwahl@fusionbox.com
License: BSD
Platform: any
